{"cleveland_dot_plots.qmd":[],"density_contours.qmd":[],"relationships.qmd":[],"grouped_bubble_charts.qmd":[],"bar_graphs.qmd":[],"overlapping_bar_graphs.qmd":[],"raincloud_plots.qmd":[],"heatmaps.qmd":[],"waffle_charts.qmd":[],"overlapping_dot_plots.qmd":[],"grouped_violin_plots.qmd":[],"histograms.qmd":[],"amounts.qmd":[],"alluvial_charts.qmd":[],"frequency_polygons.qmd":[],"hex_bins.qmd":[],"diverging_bar_graphs.qmd":[],"parallel_sets.qmd":[],"distributions.qmd":[],"instance_chart.qmd":[],"scatter_plot.qmd":[],"pie_charts.qmd":[],"beeswarm_plots.qmd":[],"dot_plots.qmd":[],"stream_plots.qmd":[],"proportions.qmd":[],"bubble_charts.qmd":[],"overlapping_histograms.qmd":[],"grp_line_graphs.qmd":[],"bins_2d.qmd":[],"index.qmd":[],"line_graphs.qmd":[],"grp_bar_graphs.qmd":[],"ridgeline_plots.qmd":[],"references.qmd":[],"dates_and_times.qmd":[],"bump_charts.qmd":[],"violin_plots.qmd":[],"sum_bar_graphs.qmd":[],"overlapping_frequency_polygons.qmd":[],"univariate.qmd":[],"grouped_box_plots.qmd":[],"overlapping_stacked_density_plots.qmd":[],"stacked_filled_density_graphs.qmd":[],"density_plots.qmd":[],"slope_graphs.qmd":[],"grouped_scatter_plots.qmd":[],"mosaic_plots.qmd":[],"box_plots.qmd":[],"xtnsns_tbl.qmd":[],"treemaps.qmd":[]}
